exmon/__init__.py
exmon/alarm.py
exmon/exceptions.py
exmon/logging.py
exmon/main.py
exmon/services/__init__.py
exmon/services/alerta.py
exmon/services/discord.py
exmon/services/service.py
exmon/services/webhook.py
exmon-0.0.1.dist-info/LICENSE
exmon-0.0.1.dist-info/METADATA
exmon-0.0.1.dist-info/WHEEL
exmon-0.0.1.dist-info/top_level.txt
exmon-0.0.1.dist-info/RECORD
