Metadata-Version: 2.1
Name: exmon
Version: 0.0.1
Summary: Exception Monitoring System
Home-page: https://github.com/klaemsch/exmon
Author: klaemsch
License: MIT
Project-URL: Bug Tracker, https://github.com/klaemsch/exmon/issues
Keywords: exception,monitoring,bug,alert,alerta,discord
Platform: UNKNOWN
Classifier: Programming Language :: Python :: 3
Classifier: License :: OSI Approved :: MIT License
Classifier: Operating System :: OS Independent
Classifier: Development Status :: 3 - Alpha
Classifier: Intended Audience :: Developers
Classifier: Topic :: Utilities
Classifier: Topic :: System :: Monitoring
Classifier: Topic :: Software Development :: Bug Tracking
Classifier: Topic :: System :: Logging
Requires-Python: >=3.8
License-File: LICENSE
Requires-Dist: requests
